{"cameraMode":{"drawMode":0,"name":"Shaded","section":"Shading Mode"},"sceneLighting":true,"audioPlay":false,"sceneViewState":{"m_AlwaysRefresh":false,"showFog":true,"showSkybox":true,"showFlares":true,"showImageEffects":true,"showParticleSystems":true,"showVisualEffectGraphs":true,"m_FxEnabled":true},"in2DMode":false,"pivot":{"x":-3.2036287784576418,"y":-8.527484893798829,"z":-0.8960111141204834},"rotation":{"x":0.024477031081914903,"y":0.9604556560516357,"z":-0.262518048286438,"w":0.08956830203533173},"size":11.47264575958252,"orthographic":false}